torch_fourier_filter/__init__.py
torch_fourier_filter/bandpass.py
torch_fourier_filter/ctf.py
torch_fourier_filter/dft_utils.py
torch_fourier_filter/dose_weight.py
torch_fourier_filter/envelopes.py
torch_fourier_filter/mtf.py
torch_fourier_filter/phase_randomize.py
torch_fourier_filter/py.typed
torch_fourier_filter/utils.py
torch_fourier_filter/whitening.py
torch_fourier_filter-0.3.4.dist-info/METADATA
torch_fourier_filter-0.3.4.dist-info/WHEEL
torch_fourier_filter-0.3.4.dist-info/licenses/LICENSE
torch_fourier_filter-0.3.4.dist-info/RECORD
