Metadata-Version: 2.4
Name: torch-fourier-filter
Version: 0.3.4
Summary: Filters for image and volumes in pyTorch
Project-URL: homepage, https://github.com/jdickerson95/torch-fourier-filter
Project-URL: repository, https://github.com/jdickerson95/torch-fourier-filter
Author-email: Josh Dickerson <jdickerson@berkeley.edu>
License: BSD-3-Clause
License-File: LICENSE
Classifier: Development Status :: 3 - Alpha
Classifier: License :: OSI Approved :: BSD License
Classifier: Programming Language :: Python :: 3
Classifier: Programming Language :: Python :: 3.10
Classifier: Programming Language :: Python :: 3.11
Classifier: Programming Language :: Python :: 3.12
Classifier: Typing :: Typed
Requires-Python: >=3.10
Requires-Dist: einops
Requires-Dist: scipy
Requires-Dist: starfile
Requires-Dist: torch
Requires-Dist: torch-ctf
Requires-Dist: torch-grid-utils
Provides-Extra: dev
Requires-Dist: ipython; extra == 'dev'
Requires-Dist: mypy; extra == 'dev'
Requires-Dist: pdbpp; extra == 'dev'
Requires-Dist: pre-commit; extra == 'dev'
Requires-Dist: rich; extra == 'dev'
Requires-Dist: ruff; extra == 'dev'
Provides-Extra: test
Requires-Dist: pytest; extra == 'test'
Requires-Dist: pytest-cov; extra == 'test'
